{
  "annotations": {
    "list": [
      {
        "builtIn": 1,
        "datasource": {
          "type": "grafana",
          "uid": "-- Grafana --"
        },
        "enable": true,
        "hide": true,
        "iconColor": "rgba(0, 211, 255, 1)",
        "name": "Annotations & Alerts",
        "type": "dashboard"
      }
    ]
  },
  "editable": true,
  "fiscalYearStartMonth": 0,
  "graphTooltip": 0,
  "id": 3,
  "links": [],
  "panels": [
    {
      "datasource": {
        "default": false,
        "type": "grafana-postgresql-datasource",
        "uid": "PCC52D03280B7034C"
      },
      "fieldConfig": {
        "defaults": {
          "color": {
            "mode": "thresholds"
          },
          "custom": {
            "align": "auto",
            "cellOptions": {
              "type": "auto"
            },
            "inspect": false
          },
          "mappings": [],
          "thresholds": {
            "mode": "absolute",
            "steps": [
              {
                "color": "green",
                "value": null
              },
              {
                "color": "red",
                "value": 80
              }
            ]
          }
        },
        "overrides": [
          {
            "matcher": {
              "id": "byName",
              "options": "schemaname"
            },
            "properties": [
              {
                "id": "custom.width",
                "value": 61
              }
            ]
          },
          {
            "matcher": {
              "id": "byName",
              "options": "relname"
            },
            "properties": [
              {
                "id": "custom.width",
                "value": 263
              }
            ]
          },
          {
            "matcher": {
              "id": "byName",
              "options": "n_live_tup"
            },
            "properties": [
              {
                "id": "custom.width",
                "value": 86
              }
            ]
          }
        ]
      },
      "gridPos": {
        "h": 8,
        "w": 10,
        "x": 0,
        "y": 0
      },
      "id": 3,
      "options": {
        "cellHeight": "sm",
        "footer": {
          "countRows": false,
          "fields": "",
          "reducer": [
            "sum"
          ],
          "show": false
        },
        "showHeader": true,
        "sortBy": []
      },
      "pluginVersion": "11.2.0",
      "targets": [
        {
          "datasource": {
            "type": "grafana-postgresql-datasource",
            "uid": "PCC52D03280B7034C"
          },
          "editorMode": "code",
          "format": "table",
          "rawQuery": true,
          "rawSql": "SELECT schemaname, relname, n_live_tup FROM pg_stat_user_tables ORDER BY n_live_tup DESC LIMIT 5;",
          "refId": "A",
          "sql": {
            "columns": [
              {
                "parameters": [],
                "type": "function"
              }
            ],
            "groupBy": [
              {
                "property": {
                  "type": "string"
                },
                "type": "groupBy"
              }
            ],
            "limit": 50
          }
        }
      ],
      "title": "Most Used Tables",
      "type": "table"
    },
    {
      "datasource": {
        "default": false,
        "type": "grafana-postgresql-datasource",
        "uid": "PCC52D03280B7034C"
      },
      "fieldConfig": {
        "defaults": {
          "mappings": [],
          "thresholds": {
            "mode": "percentage",
            "steps": [
              {
                "color": "green",
                "value": null
              },
              {
                "color": "orange",
                "value": 70
              },
              {
                "color": "red",
                "value": 85
              }
            ]
          }
        },
        "overrides": []
      },
      "gridPos": {
        "h": 4,
        "w": 5,
        "x": 10,
        "y": 0
      },
      "id": 4,
      "options": {
        "minVizHeight": 75,
        "minVizWidth": 75,
        "orientation": "auto",
        "reduceOptions": {
          "calcs": [
            "lastNotNull"
          ],
          "fields": "",
          "values": false
        },
        "showThresholdLabels": false,
        "showThresholdMarkers": true,
        "sizing": "auto"
      },
      "pluginVersion": "11.2.0",
      "targets": [
        {
          "datasource": {
            "type": "grafana-postgresql-datasource",
            "uid": "PCC52D03280B7034C"
          },
          "editorMode": "code",
          "format": "table",
          "rawQuery": true,
          "rawSql": "SELECT count(*) FROM pg_stat_activity WHERE state = 'active';",
          "refId": "A",
          "sql": {
            "columns": [
              {
                "parameters": [],
                "type": "function"
              }
            ],
            "groupBy": [
              {
                "property": {
                  "type": "string"
                },
                "type": "groupBy"
              }
            ],
            "limit": 50
          }
        }
      ],
      "title": "Active Connections",
      "type": "gauge"
    },
    {
      "datasource": {
        "default": false,
        "type": "grafana-postgresql-datasource",
        "uid": "PCC52D03280B7034C"
      },
      "fieldConfig": {
        "defaults": {
          "mappings": [],
          "thresholds": {
            "mode": "absolute",
            "steps": [
              {
                "color": "green",
                "value": null
              },
              {
                "color": "red",
                "value": 80
              }
            ]
          },
          "unit": "short"
        },
        "overrides": []
      },
      "gridPos": {
        "h": 4,
        "w": 5,
        "x": 15,
        "y": 0
      },
      "id": 1,
      "options": {
        "colorMode": "none",
        "graphMode": "area",
        "justifyMode": "auto",
        "orientation": "auto",
        "percentChangeColorMode": "standard",
        "reduceOptions": {
          "calcs": [],
          "fields": "/.*/",
          "values": true
        },
        "showPercentChange": false,
        "textMode": "auto",
        "wideLayout": true
      },
      "pluginVersion": "11.2.0",
      "targets": [
        {
          "datasource": {
            "type": "grafana-postgresql-datasource",
            "uid": "PCC52D03280B7034C"
          },
          "editorMode": "code",
          "format": "table",
          "rawQuery": true,
          "rawSql": "SELECT pg_size_pretty(pg_database_size('test_db'));",
          "refId": "A",
          "sql": {
            "columns": [
              {
                "parameters": [],
                "type": "function"
              }
            ],
            "groupBy": [
              {
                "property": {
                  "type": "string"
                },
                "type": "groupBy"
              }
            ],
            "limit": 50
          }
        }
      ],
      "title": "Database Size",
      "type": "stat"
    },
    {
      "datasource": {
        "default": false,
        "type": "grafana-postgresql-datasource",
        "uid": "PCC52D03280B7034C"
      },
      "fieldConfig": {
        "defaults": {
          "mappings": [],
          "thresholds": {
            "mode": "percentage",
            "steps": [
              {
                "color": "green",
                "value": null
              },
              {
                "color": "orange",
                "value": 70
              },
              {
                "color": "red",
                "value": 85
              }
            ]
          }
        },
        "overrides": []
      },
      "gridPos": {
        "h": 4,
        "w": 5,
        "x": 10,
        "y": 4
      },
      "id": 2,
      "options": {
        "minVizHeight": 75,
        "minVizWidth": 75,
        "orientation": "auto",
        "reduceOptions": {
          "calcs": [
            "lastNotNull"
          ],
          "fields": "",
          "values": false
        },
        "showThresholdLabels": false,
        "showThresholdMarkers": true,
        "sizing": "auto"
      },
      "pluginVersion": "11.2.0",
      "targets": [
        {
          "datasource": {
            "type": "grafana-postgresql-datasource",
            "uid": "PCC52D03280B7034C"
          },
          "editorMode": "code",
          "format": "table",
          "rawQuery": true,
          "rawSql": "SELECT count(*) FROM information_schema.tables WHERE table_schema = 'public';",
          "refId": "A",
          "sql": {
            "columns": [
              {
                "parameters": [],
                "type": "function"
              }
            ],
            "groupBy": [
              {
                "property": {
                  "type": "string"
                },
                "type": "groupBy"
              }
            ],
            "limit": 50
          }
        }
      ],
      "title": "Number of Tables",
      "type": "gauge"
    },
    {
      "datasource": {
        "default": false,
        "type": "grafana-postgresql-datasource",
        "uid": "PCC52D03280B7034C"
      },
      "fieldConfig": {
        "defaults": {
          "color": {
            "mode": "thresholds"
          },
          "custom": {
            "align": "auto",
            "cellOptions": {
              "type": "auto"
            },
            "inspect": false
          },
          "mappings": [],
          "thresholds": {
            "mode": "absolute",
            "steps": [
              {
                "color": "green",
                "value": null
              },
              {
                "color": "red",
                "value": 80
              }
            ]
          }
        },
        "overrides": [
          {
            "matcher": {
              "id": "byName",
              "options": "query"
            },
            "properties": [
              {
                "id": "custom.width",
                "value": 396
              }
            ]
          },
          {
            "matcher": {
              "id": "byName",
              "options": "state"
            },
            "properties": [
              {
                "id": "custom.width",
                "value": 62
              }
            ]
          }
        ]
      },
      "gridPos": {
        "h": 4,
        "w": 10,
        "x": 0,
        "y": 8
      },
      "id": 5,
      "options": {
        "cellHeight": "sm",
        "footer": {
          "countRows": false,
          "fields": "",
          "reducer": [
            "sum"
          ],
          "show": false
        },
        "showHeader": true,
        "sortBy": []
      },
      "pluginVersion": "11.2.0",
      "targets": [
        {
          "datasource": {
            "type": "grafana-postgresql-datasource",
            "uid": "PCC52D03280B7034C"
          },
          "editorMode": "code",
          "format": "table",
          "rawQuery": true,
          "rawSql": "SELECT \n    query,\n    state,\n    now() - xact_start AS duration\nFROM \n    pg_stat_activity\nWHERE \n    state != 'idle'\n    AND state != 'idle in transaction (aborted)'\nORDER BY \n    duration DESC\nLIMIT 5;\n",
          "refId": "A",
          "sql": {
            "columns": [
              {
                "parameters": [],
                "type": "function"
              }
            ],
            "groupBy": [
              {
                "property": {
                  "type": "string"
                },
                "type": "groupBy"
              }
            ],
            "limit": 50
          }
        }
      ],
      "title": "Longuest Running Query",
      "type": "table"
    }
  ],
  "refresh": "",
  "schemaVersion": 39,
  "tags": [],
  "templating": {
    "list": []
  },
  "time": {
    "from": "2024-09-03T06:22:02.298Z",
    "to": "2024-09-03T18:22:02.298Z"
  },
  "timepicker": {},
  "timezone": "browser",
  "title": "Postgres Dashboard",
  "uid": "adwsnwf5stxq8e",
  "version": 1,
  "weekStart": ""
}